README.rst
setup.py
yajl/__init__.py
yajl/yajl_common.py
yajl/yajl_gen.py
yajl/yajl_parse.py
yajl_py.egg-info/PKG-INFO
yajl_py.egg-info/SOURCES.txt
yajl_py.egg-info/dependency_links.txt
yajl_py.egg-info/entry_points.txt
yajl_py.egg-info/requires.txt
yajl_py.egg-info/top_level.txt
yajl_py.egg-info/zip-safe