Metadata-Version: 1.0
Name: yajl-py
Version: 2.1.2
Summary: Pure Python Yajl Wrapper
Home-page: http://pykler.github.com/yajl-py/
Author: Hatem Nassrat
Author-email: hnassrat@gmail.com
License: PSF
Keywords: yajl json parsing
Platform: UNKNOWN
